ndustrialio/__init__.py
ndustrialio/apiservices/__init__.py
ndustrialio/apiservices/contxt.py
ndustrialio/apiservices/costcenters.py
ndustrialio/apiservices/events.py
ndustrialio/apiservices/facilities.py
ndustrialio/apiservices/feeds.py
ndustrialio/apiservices/flywheeling.py
ndustrialio/apiservices/health.py
ndustrialio/apiservices/ngest.py
ndustrialio/apiservices/opsmetric.py
ndustrialio/apiservices/rates.py
ndustrialio/apiservices/weather.py
ndustrialio/apiservices/workers.py
ndustrialio/apiservices/helpers/__init__.py
ndustrialio/apiservices/helpers/field_metrics.py
ndustrialio/workertools/__init__.py
ndustrialio/workertools/api.py
ndustrialio/workertools/cassandra_utility.py
ndustrialio/workertools/ngest.py
ndustrialio/workertools/postgres_utility.py
ndustrialio/workertools/query.py
ndustrialio/workertools/sftp.py
ndustrialio/workertools/slack_utility.py
setec_ndustrialio_python-0.2.dist-info/METADATA
setec_ndustrialio_python-0.2.dist-info/WHEEL
setec_ndustrialio_python-0.2.dist-info/top_level.txt
setec_ndustrialio_python-0.2.dist-info/RECORD
