Metadata-Version: 2.1
Name: setec-ndustrialio-python
Version: 0.2
Summary: API bindings and worker tools for </ndustrial.io>
Home-page: http://github.com/ndustrialio/ndustrialio-python
Author: John Hunt
Author-email: jhunt@ndustrial.io
License: UNKNOWN
Platform: UNKNOWN
Requires-Dist: pytz
Requires-Dist: tzlocal
Requires-Dist: requests
Requires-Dist: scipy
Requires-Dist: numpy
